Snippify/__init__.py
Snippify/__builtins/__data.py
Snippify/__builtins/__errors.py
Snippify/__builtins/__init__.py
Snippify/__builtins/__parsers.py
Snippify/__builtins/__snip_utils.py
Snippify/__builtins/__verify.py
Snippify/core/__init__.py
Snippify/core/settings.py
Snippify/core/snippet.py
Snippify-1.0.2.dist-info/LICENSE
Snippify-1.0.2.dist-info/METADATA
Snippify-1.0.2.dist-info/WHEEL
Snippify-1.0.2.dist-info/top_level.txt
Snippify-1.0.2.dist-info/RECORD
