Metadata-Version: 2.1
Name: Snippify
Version: 1.0.2
Summary: Project Snippify: Create, Save, Use Snippets Easily, directly in the comfort zone of your terminal or your code.
Author-email: Aditya Gaur <adityagaur.home@gmail.com>
License: GNU GENERAL PUBLIC LICENSE
Project-URL: Homepage, https://github.com/xdityagr/Snippify
Keywords: Snippify,Snippet Maker,Snippet Manager,Code Snippets,Project Snippify
Requires-Python: >=3.8
License-File: LICENSE
Requires-Dist: colorama
Requires-Dist: pyboxen
Requires-Dist: pynput
Requires-Dist: pyperclip
Requires-Dist: tabulate
